{
    "help": {
        "category": "🤖Botコマンド",
        "usage" : "help",
        "info": "コマンドリストを表示します。"
    },
    "invite": {
        "category": "🤖Botコマンド",
        "usage" : "invite",
        "info": "Akane招待リンクを表示します。"
    },
    "ping": {
	    "category": "🤖Botコマンド",
	    "usage" : "ping",
	    "info": "AkaneのPingを表示します。"
    },
    "cat": {
        "category": "⭐機能系コマンド",
        "usage" : "cat",
        "info": "にゃーん"
    },
    "dice": {
        "category": "⭐機能系コマンド",
        "usage" : "dice",
        "info": "1~6の目があるサイコロを振ります。"
    },
    "kuji": {
        "category": "⭐機能系コマンド",
        "usage" : "kuji",
        "info": "おみくじを引きます。"
    },
    "gosen": {
        "category": "⭐機能系コマンド",
        "usage" : "gosen",
        "info": "「5000兆円欲しい！」を作成します。"
    },
    "janken": {
        "category": "⭐機能系コマンド",
        "usage" : "janken",
        "info": "Akaneとじゃんけんをします。"
    },
    "unban": {
        "category": "⭐機能系コマンド",
        "usage" : "unban <ユーザーをメンションorユーザーID>",
        "info": "ユーザーのBANを解除します。（管理者権限で実行必須）"
    },
    "ytdl": {
          "category": "⭐機能系コマンド",
          "usage" : "ytdl <URL>",
          "info": "YouTube動画のダウンロードリンクを取得します"
    },
    "scinfo": {
          "category": "⭐機能系コマンド",
          "usage" : "scinfo <ユーザー名>",
          "info": "Scratchのユーザー情報を取得します"
    },
    "scff": {
          "category": "⭐機能系コマンド",
          "usage" : "scff <モード> <対象ユーザー> <確認するユーザー>",
          "info": "Scratchのユーザーフォロー・被フォロー状況を取得します"
    },
    "fixtweet": {
          "category": "⭐機能系コマンド",
          "usage" : "fixtweet",
          "info": "ツイートの自動展開機能を有効化・無効化します"
    }
}